netports/__init__.py
netports/exceptions.py
netports/helpers.py
netports/intf.py
netports/intf_gm.py
netports/intf_map.py
netports/ip.py
netports/item.py
netports/mac.py
netports/ports.py
netports/py.typed
netports/range.py
netports/static.py
netports/swversion.py
netports/tcp.py
netports/types_.py
netports/vlan.py
netports-0.15.0.dist-info/METADATA
netports-0.15.0.dist-info/WHEEL
netports-0.15.0.dist-info/RECORD
