Metadata-Version: 2.1
Name: netports
Version: 0.15.0
Summary: Python tools for managing ranges of VLANs, TCP/UDP ports, IP protocols, Interfaces
Home-page: https://github.com/vladimirs-git/netports
License: Apache-2.0
Keywords: networking,port,range,tcp,udp,vlan,ip
Author: Vladimirs Prusakovs
Author-email: vladimir.prusakovs@gmail.com
Requires-Python: >=3.8,<4.0
Classifier: Development Status :: 5 - Production/Stable
Classifier: Intended Audience :: Developers
Classifier: License :: OSI Approved :: Apache Software License
Classifier: Natural Language :: English
Classifier: Programming Language :: Python :: 3
Classifier: Programming Language :: Python :: 3.8
Classifier: Programming Language :: Python :: 3.9
Classifier: Programming Language :: Python :: 3.10
Classifier: Programming Language :: Python :: 3.11
Classifier: Programming Language :: Python :: 3.12
Classifier: Topic :: System :: Networking
Provides-Extra: test
Requires-Dist: packaging (>=23.2,<24.0)
Requires-Dist: pydantic (>=2.8.2,<3.0.0)
Project-URL: Bug Tracker, https://github.com/vladimirs-git/netports/issues
Project-URL: Download URL, https://github.com/vladimirs-git/netports/archive/refs/tags/0.15.0.tar.gz
Project-URL: Repository, https://github.com/vladimirs-git/netports
